gspread_models/__init__.py
gspread_models/base.py
gspread_models/date_parser.py
gspread_models/service.py
gspread_models-1.0.7.dist-info/LICENSE
gspread_models-1.0.7.dist-info/METADATA
gspread_models-1.0.7.dist-info/WHEEL
gspread_models-1.0.7.dist-info/top_level.txt
gspread_models-1.0.7.dist-info/RECORD
