Metadata-Version: 2.1
Name: gspread_models
Version: 1.0.7
Summary: An Object Relational Mapper (ORM) for the Google Sheets API. Provides a straightforward and intuitive model-based query interface, making it easy to interact with Google Sheets as if it were more like a database. Offers a fast and flexible way to get up and running with a Google Sheets database, for rapid prototyping and development in Python.
Home-page: https://github.com/s2t2/gspread-models-py
Author: Michael Rossetti
Author-email: datacreativellc@gmail.com
License: MIT
Keywords: google sheets gspread models orm spreadsheet google-sheets google-sheets-api gspread-models gspread_models
License-File: LICENSE
Requires-Dist: python-dotenv
Requires-Dist: gspread >=6.0.2
